README.rst
mgoquery.py
setup.py
MgoQuery.egg-info/PKG-INFO
MgoQuery.egg-info/SOURCES.txt
MgoQuery.egg-info/dependency_links.txt
MgoQuery.egg-info/requires.txt
MgoQuery.egg-info/top_level.txt