Metadata-Version: 1.0
Name: MgoQuery
Version: 0.5.5
Summary: A concise language parser for creating MongoDB queries
Home-page: https://bitbucket.org/elarson/mgoquery
Author: Eric Larson
Author-email: eric@ionrock.org
License: UNKNOWN
Platform: UNKNOWN
